{"name":"Cup","tagline":"Cappuccino UI and controller for jQuery File Upload","body":"## Fork of Cup\r\n\r\n**Cup** (Cappuccino Uploader) is a [Cappuccino](http://www.cappuccino-project.org) framework that wraps the fantastic [jQuery File Upload](http://blueimp.github.io/jQuery-File-Upload/) library. Best of all, because it’s based on Cappuccino technologies like KVO and bindings, it needs very little code to make it work.\r\n\r\nFor information on installation and usage, please see the [wiki](https://github.com/aparajita/Cup/wiki).\r\n\r\nThis fork is not intended to replace Aparajitas equally fantastic ObjectiveJ Cappuccino uploader framework [Cup](https://github.com/aparajita/Cup). It is here only to provide a sandbox for testing new features that may or may not be included in the original repos.\r\n\r\nGitHup page: http://kerusan.github.io/Cup\r\n","google":"","note":"Don't delete this file! It's used internally to help with page regeneration."}